{
  "main": {
    "id": "9fa7dfeed4b56812",
    "type": "split",
    "children": [
      {
        "id": "0da59ff6ee0ba2e7",
        "type": "tabs",
        "children": [
          {
            "id": "e3882c4c994a8617",
            "type": "leaf",
            "state": {
              "type": "empty",
              "state": {}
            }
          }
        ]
      }
    ],
    "direction": "vertical"
  },
  "left": {
    "id": "55b628949e7b67d1",
    "type": "split",
    "children": [
      {
        "id": "71b26add7c756996",
        "type": "tabs",
        "children": [
          {
            "id": "e580fae59e9a9ea9",
            "type": "leaf",
            "state": {
              "type": "file-explorer",
              "state": {
                "sortOrder": "alphabetical"
              }
            }
          },
          {
            "id": "a0d10ddd8e753934",
            "type": "leaf",
            "state": {
              "type": "search",
              "state": {
                "query": "tag:list",
                "matchingCase": false,
                "explainSearch": false,
                "collapseAll": false,
                "extraContext": false,
                "sortOrder": "alphabetical"
              }
            }
          },
          {
            "id": "63e902be1dec2dfb",
            "type": "leaf",
            "state": {
              "type": "bookmarks",
              "state": {}
            }
          },
          {
            "id": "cbf6067f674a349b",
            "type": "leaf",
            "state": {
              "type": "mk-file-view",
              "state": {}
            }
          },
          {
            "id": "08cf69e49b6649ca",
            "type": "leaf",
            "state": {
              "type": "mk-path-view",
              "state": {}
            }
          }
        ],
        "currentTab": 4
      }
    ],
    "direction": "horizontal",
    "width": 297.5
  },
  "right": {
    "id": "34ff48ef87a59689",
    "type": "split",
    "children": [
      {
        "id": "58207a933dbe86fd",
        "type": "tabs",
        "children": [
          {
            "id": "6c2073609bcafc03",
            "type": "leaf",
            "state": {
              "type": "tag",
              "state": {
                "sortOrder": "frequency",
                "useHierarchy": true
              }
            }
          },
          {
            "id": "59c591a33c12ad64",
            "type": "leaf",
            "state": {
              "type": "outline",
              "state": {}
            }
          },
          {
            "id": "0f0f9c49db70aabd",
            "type": "leaf",
            "state": {
              "type": "advanced-tables-toolbar",
              "state": {}
            }
          },
          {
            "id": "109f864c3821e87d",
            "type": "leaf",
            "state": {
              "type": "calendar",
              "state": {}
            }
          },
          {
            "id": "3ae6a945bd95e1a6",
            "type": "leaf",
            "state": {
              "type": "smart-connections-view",
              "state": {}
            }
          },
          {
            "id": "c20f6a0b90e37cb6",
            "type": "leaf",
            "state": {
              "type": "smart-connections-chat-view",
              "state": {}
            }
          }
        ],
        "currentTab": 2
      }
    ],
    "direction": "horizontal",
    "width": 280.5,
    "collapsed": true
  },
  "left-ribbon": {
    "hiddenItems": {
      "switcher:퀵 스위처 열기": false,
      "graph:그래프 뷰 열기": false,
      "canvas:새 캔버스 만들기": false,
      "templates:템플릿 삽입": false,
      "command-palette:명령어 팔레트 열기": false,
      "table-editor-obsidian:Advanced Tables Toolbar": false,
      "obsidian-excalidraw-plugin:Create new drawing": false,
      "smart-connections:Open: View Smart Connections": false,
      "smart-connections:Open: Smart Chat Conversation": false
    }
  },
  "active": "0f0f9c49db70aabd",
  "lastOpenFiles": [
    "smart-chats",
    "Tags",
    "Java/JAVA 14+/Enhanced Switch Expressions.md",
    "알고리즘/압축/산술부호화(Arithmetic Coding).md",
    "알고리즘/압축/RLE(Run-Length Encodeing)알고리즘.md",
    "알고리즘/압축/LZW(Lempel-Ziv-Welch).md",
    "아스키 코드 ASCII.md",
    "Java/COLLECTIONS/LIST.md",
    "Java/COLLECTIONS/다중 리스트.md",
    "Java/COLLECTIONS/COLLECTIONS.md",
    "Java/Arrays.md",
    "알고리즘/문자열 탐색 알고리즘/라빈-카프.md",
    "알고리즘/문자열 탐색 알고리즘/KMP(Knuth-Mottis-Pratt) 문자열 검색 알고리즘.md",
    "알고리즘/피보나치/O(2pN) 재귀.md",
    "알고리즘/GCD(Greatest Common Divisor).md",
    "알고리즘/Permutation - 순열.md",
    "알고리즘/알고리즘.md",
    "Dart/Dart.md",
    "알고리즘/피보나치/O(log n) 행렬/O(log n) 행렬로 구하기.md",
    "알고리즘/피보나치/O(log n) 행렬/피보나치 행렬.md",
    "알고리즘/문자열 탐색 알고리즘/보이어-무어.md",
    "과제 정리/과제 정리.md",
    "Excalidraw/Excalidraw.md",
    "Java/소수점 표현 방법.md",
    "알고리즘/문자열 탐색 알고리즘/Trie.md",
    "알고리즘/문자열 탐색 알고리즘/문자열 탐색 알고리즘.md",
    "알고리즘/문자열 탐색 알고리즘/아호-코라식.md",
    "desktop.ini",
    "Excalidraw",
    "스터디 정리/백엔드 안드로이드",
    "스터디 정리",
    "과제 정리",
    "Goggle Colaboratory",
    "이미지/Pasted image 20231116051855.png",
    "Pasted image 20231112215440.png",
    "Pasted image 20231112215455.png",
    "이미지/다운로드.png",
    "Context/spacesLastSync (conflict 2023-10-12-18-14-38).log",
    "Context/spacesLastSync (conflict 2023-10-12-17-12-33).log",
    "Context/spacesLastSync (conflict 2023-10-12-15-35-52).log",
    "무제 파일.canvas",
    "이미지/Favicon.png",
    "이미지/open graph.png",
    "이미지/js_alert.png",
    "무제 파일 1.canvas",
    "이미지/tree.png",
    "이미지/삼각형.png",
    "이미지/오른손 법칙.png"
  ]
}